<TrID ver="2.00">
	<Info>
		<FileType>General CADD Pro (generic)</FileType>
		<Ext>GXD</Ext>
		<Mime>application/octet-stream</Mime>
		<ExtraInfo>
			<Rem>Match drawings, components, fonts, etc.</Rem>
			<RefURL>http://www.generalcadd.com/</RefURL>
		</ExtraInfo>
		<User>Marco Pontello</User>
		<E-Mail>marcopon@gmail.com</E-Mail>
		<Home>http://mark0.net</Home>
	</Info>
	<General>
		<FileNum>18</FileNum>
		<Date>
			<Year>2015</Year>
			<Month>2</Month>
			<Day>21</Day>
		</Date>
		<Time>
			<Hour>20</Hour>
			<Min>30</Min>
			<Sec>44</Sec>
		</Time>
		<Creator>TrIDScan/Py v1.92</Creator>
	</General>
	<FrontBlock>
		<Pattern>
			<Bytes>1F8B080000000000000B47584400</Bytes>
			<ASCII> . . . . . . . . . . G X D</ASCII>
			<Pos>0</Pos>
		</Pattern>
		<Pattern>
			<Bytes>40</Bytes>
			<ASCII> @</ASCII>
			<Pos>39</Pos>
		</Pattern>
		<Pattern>
			<Bytes>0000250000004372656174656420776974682047656E6572616C204341444420666F722057696E646F7773</Bytes>
			<ASCII> . . % . . . C r e a t e d   w i t h   G e n e r a l   C A D D   f o r   W i n d o w s</ASCII>
			<Pos>54</Pos>
		</Pattern>
	</FrontBlock>
</TrID>