<TrID ver="2.00">
	<Info>
		<FileType>M.O.N Old module</FileType>
		<Ext>MON</Ext>
		<Mime>audio/x-mod</Mime>
		<ExtraInfo>
			<Rem>Music format created by Charles Deenen, used by the Maniacs of Noise.</Rem>
			<RefURL>http://www.exotica.org.uk/wiki/M.O.N_Old</RefURL>
		</ExtraInfo>
		<User>Marco Pontello</User>
		<E-Mail>marcopon@gmail.com</E-Mail>
		<Home>http://mark0.net</Home>
	</Info>
	<General>
		<FileNum>12</FileNum>
		<Refine>7 by Marco Pontello</Refine>
		<CheckStrings>True</CheckStrings>
		<Date>
			<Year>2015</Year>
			<Month>4</Month>
			<Day>7</Day>
		</Date>
		<Time>
			<Hour>17</Hour>
			<Min>8</Min>
			<Sec>48</Sec>
		</Time>
		<Creator>TrIDScan/Py v2.01</Creator>
	</General>
	<FrontBlock>
		<Pattern>
			<Bytes>0239000100</Bytes>
			<ASCII> . 9</ASCII>
			<Pos>0</Pos>
		</Pattern>
		<Pattern>
			<Bytes>66024E757800183900</Bytes>
			<ASCII> f . N u x . . 9</ASCII>
			<Pos>8</Pos>
		</Pattern>
	</FrontBlock>
	<GlobalStrings>
		<String>X'R'P'P'P'P</String>
	</GlobalStrings>
</TrID>