<TrID ver="2.00">
	<Info>
		<FileType>Infinity Engine Animation (v2)</FileType>
		<Ext>BAM</Ext>
		<Mime>application/octet-stream</Mime>
		<ExtraInfo>
			<Rem></Rem>
			<RefURL>http://gibberlings3.net/iesdp/file_formats/ie_formats/bam_v2.htm</RefURL>
		</ExtraInfo>
		<User>Marco Pontello</User>
		<E-Mail>marcopon@gmail.com</E-Mail>
		<Home>http://mark0.net</Home>
	</Info>
	<General>
		<FileNum>2</FileNum>
		<Date>
			<Year>2017</Year>
			<Month>11</Month>
			<Day>7</Day>
		</Date>
		<Time>
			<Hour>21</Hour>
			<Min>20</Min>
			<Sec>36</Sec>
		</Time>
		<Creator>TrIDScan/Py v2.02</Creator>
	</General>
	<FrontBlock>
		<Pattern>
			<Bytes>42414D20563220</Bytes>
			<ASCII> B A M   V 2</ASCII>
			<Pos>0</Pos>
		</Pattern>
	</FrontBlock>
</TrID>