<TrID ver="2.00">
	<Info>
		<FileType>Infinity Engine save Game (generic)</FileType>
		<Ext>GAM</Ext>
		<Mime>application/octet-stream</Mime>
		<ExtraInfo>
			<Rem>Infinity Engine GAM files hold game information in save games.</Rem>
			<RefURL>http://iesdp.gibberlings3.net/file_formats/ie_formats/gam_v2.0.htm</RefURL>
		</ExtraInfo>
		<User>Sam.</User>
		<E-Mail>sampsca@yahoo.com</E-Mail>
		<Home>http://www.shsforums.net/user/10485-sam/</Home>
	</Info>
	<General>
		<FileNum>141</FileNum>
		<Refine>9 by Marco Pontello</Refine>
		<Date>
			<Year>2017</Year>
			<Month>11</Month>
			<Day>7</Day>
		</Date>
		<Time>
			<Hour>21</Hour>
			<Min>2</Min>
			<Sec>43</Sec>
		</Time>
		<Creator>TrIDScan/Py v2.02</Creator>
	</General>
	<FrontBlock>
		<Pattern>
			<Bytes>47414D4556</Bytes>
			<ASCII> G A M E V</ASCII>
			<Pos>0</Pos>
		</Pattern>
		<Pattern>
			<Bytes>2E</Bytes>
			<Pos>6</Pos>
		</Pattern>
	</FrontBlock>
</TrID>