<TrID ver="2.00">
	<Info>
		<FileType>Sage Binary</FileType>
		<Ext>SAB</Ext>
		<Mime>application/octet-stream</Mime>
		<ExtraInfo>
			<Rem></Rem>
			<RefURL>https://en.wikipedia.org/wiki/Symbolics</RefURL>
		</ExtraInfo>
		<User>Marco Pontello</User>
		<E-Mail>marcopon@gmail.com</E-Mail>
		<Home>https://mark0.net</Home>
	</Info>
	<General>
		<FileNum>644</FileNum>
		<CheckStrings>True</CheckStrings>
		<Date>
			<Year>2020</Year>
			<Month>4</Month>
			<Day>5</Day>
		</Date>
		<Time>
			<Hour>13</Hour>
			<Min>35</Min>
			<Sec>56</Sec>
		</Time>
		<Creator>TrIDScan/Py v2.02</Creator>
	</General>
	<FrontBlock>
		<Pattern>
			<Bytes>00000000071F0D09000D0200200B13434F4D50494C4154494F4E2D555345522D49440B</Bytes>
			<ASCII> . . . . . . . . . . . .   . . C O M P I L A T I O N - U S E R - I D</ASCII>
			<Pos>0</Pos>
		</Pattern>
	</FrontBlock>
	<GlobalStrings>
		<String>COMPILATION-SYSTEM-VERSION</String>
		<String>COMPILATION-SAGE-VERSION</String>
		<String>LOGICAL-SOURCE-PATHNAME</String>
		<String>FILE-ATTRIBUTE-STRING</String>
		<String>MODIFICATION-HISTORY$</String>
		<String>COMPILATION-MACHINE</String>
		<String>COMPILATION-USER-ID</String>
		<String>COMPILATION-TIME</String>
		<String>LOGICAL-PATHNAME</String>
		<String>VERSION-NUMBER</String>
		<String>RELEASENUMBER</String>
		<String>SOURCE-TOPIC</String>
		<String>CALLEE-LIST</String>
		<String>UNIQUE-ID</String>
		<String>CONTENTS</String>
		<String>KEYWORDS</String>
		<String>ONELINER</String>
		<String>TRUENAME</String>
		<String>PACKAGE</String>
		<String>RELATED</String>
		<String>TOKENS%</String>
		<String>SYNTAX</String>
		<String>.SAB.</String>
		<String>NOTES</String>
		<String>LISP</String>
	</GlobalStrings>
</TrID>