<TrID ver="2.00">
	<Info>
		<FileType>Twistpad Syntax highlight script</FileType>
		<Ext>SDF</Ext>
		<Mime>text/ini</Mime>
		<ExtraInfo>
			<Rem></Rem>
			<RefURL>https://www.carthagosoft.net/Twistpad.php</RefURL>
		</ExtraInfo>
		<User>Marco Pontello</User>
		<E-Mail>marcopon@gmail.com</E-Mail>
		<Home>https://mark0.net</Home>
	</Info>
	<General>
		<FileNum>54</FileNum>
		<CheckStrings>True</CheckStrings>
		<Date>
			<Year>2025</Year>
			<Month>3</Month>
			<Day>23</Day>
		</Date>
		<Time>
			<Hour>14</Hour>
			<Min>6</Min>
			<Sec>37</Sec>
		</Time>
		<Creator>TrIDScan/Py v2.02</Creator>
	</General>
	<FrontBlock>
		<Pattern>
			<Bytes>3B</Bytes>
			<ASCII> ;</ASCII>
			<Pos>0</Pos>
		</Pattern>
	</FrontBlock>
	<GlobalStrings>
		<String>SYNTAX HIGHLIGHT SCRIPT FOR TWISTPAD</String>
		<String>WHOLEWORDONLY</String>
		<String>EXTENSIONS</String>
		<String>SYNTAXNAME</String>
		<String>STARTSTOP</String>
		<String>PRIORITY</String>
		<String>SPELLING</String>
		<String>CONTEXT</String>
		<String>HEADER</String>
		<String>FIRST</String>
		<String>LAST</String>
		<String>TYPE</String>
	</GlobalStrings>
</TrID>