<TrID ver="2.00">
	<Info>
		<FileType>Sublime Text Mouse settings</FileType>
		<Ext>SUBLIME-MOUSEMAP</Ext>
		<Mime>text/plain</Mime>
		<ExtraInfo>
			<Rem></Rem>
			<RefURL>https://en.wikipedia.org/wiki/Sublime_Text</RefURL>
		</ExtraInfo>
		<User>Marco Pontello</User>
		<E-Mail>marcopon@gmail.com</E-Mail>
		<Home>https://mark0.net</Home>
	</Info>
	<General>
		<FileNum>8</FileNum>
		<Refine>2 by Marco Pontello</Refine>
		<CheckStrings>True</CheckStrings>
		<Date>
			<Year>2023</Year>
			<Month>12</Month>
			<Day>3</Day>
		</Date>
		<Time>
			<Hour>0</Hour>
			<Min>27</Min>
			<Sec>40</Sec>
		</Time>
		<Creator>TrIDScan/Py v2.02</Creator>
	</General>
	<FrontBlock>
		<Pattern>
			<Bytes>5B</Bytes>
			<ASCII> [</ASCII>
			<Pos>0</Pos>
		</Pattern>
	</FrontBlock>
	<GlobalStrings>
		<String>PRESS_COMMAND</String>
		<String>PRESS_ARGS</String>
		<String>MODIFIERS</String>
		<String>BUTTON1</String>
		<String>ATION</String>
		<String>DRAG</String>
	</GlobalStrings>
</TrID>