<TrID ver="2.00">
	<Info>
		<FileType>DVDStyler Project</FileType>
		<Ext>DVDS</Ext>
		<ExtraInfo>
			<Rem></Rem>
			<RefURL>http://www.dvdstyler.org/</RefURL>
		</ExtraInfo>
		<User>Marco Pontello</User>
		<E-Mail>marcopon@gmail.com</E-Mail>
		<Home>http://mark0.net</Home>
	</Info>
	<General>
		<FileNum>4</FileNum>
		<CheckStrings>True</CheckStrings>
		<Date>
			<Year>2014</Year>
			<Month>6</Month>
			<Day>3</Day>
		</Date>
		<Time>
			<Hour>2</Hour>
			<Min>54</Min>
			<Sec>42</Sec>
		</Time>
		<Creator>TrIDScan/Py v1.90</Creator>
	</General>
	<FrontBlock>
		<Pattern>
			<Bytes>3C3F786D6C2076657273696F6E3D22312E3022</Bytes>
			<ASCII> . ? x m l   v e r s i o n = " 1 . 0 "</ASCII>
			<Pos>0</Pos>
		</Pattern>
		<Pattern>
			<Bytes>656E636F64696E673D227574662D38223F3E0A</Bytes>
			<ASCII> e n c o d i n g = " u t f - 8 " ?</ASCII>
			<Pos>20</Pos>
		</Pattern>
	</FrontBlock>
	<GlobalStrings>
		<String>DVDSTYLER VIDEOBITRATE</String>
		<String>PARAMETER HIGHLIGHTED</String>
		<String>DOMINANT-BASELINE</String>
		<String>MENU ASPECTRATIO</String>
		<String>SUBPICTURE LANG</String>
		<String>OBJECT DEFSIZE</String>
		<String>STROKE-OPACITY</String>
		<String>AUDIO FORMAT</String>
		<String>STROKE-WIDTH</String>
		<String>VIDEO ASPECT</String>
		<String>VIDEO FORMAT</String>
		<String>AUDIOFORMAT</String>
		<String>FONT-FAMILY</String>
		<String>FONT-WEIGHT</String>
		<String>IMAGE XLINK</String>
		<String>TEXT-ANCHOR</String>
		<String>VIDEOFORMAT</String>
		<String>XML VERSION</String>
		<String>AUDIO LANG</String>
		<String>BACKGROUND</String>
		<String>FONT-STYLE</String>
		<String>INTERLACED</String>
		<String>RECT STYLE</String>
		<String>TEXT STYLE</String>
		<String>WIDESCREEN</String>
		<String>BUTTON ID</String>
		<String>EMPTYMENU</String>
		<String>FONT-SIZE</String>
		<String>PGC ENTRY</String>
		<String>SVG WIDTH</String>
		<String>USE XLINK</String>
		<String>CAPACITY</String>
		<String>ENCODING</String>
		<String>FILENAME</String>
		<String>SELECTED</String>
		<String>TEMPLATE</String>
		<String>TITLESET</String>
		<String>VOB FILE</String>
		<String>DEFS ID</String>
		<String>JUMPPAD</String>
		<String>ACTION</String>
		<String>HEIGHT</String>
		<String>NORMAL</String>
		<String>SVG ID</String>
		<String>MENUS</String>
		<String>UTF-8</String>
		<String>FILL</String>
		<String>HREF</String>
		<String>NONE</String>
		<String>POST</String>
		<String>ROOT</String>
		<String>VMGM</String>
	</GlobalStrings>
</TrID>