<TrID ver="2.00">
	<Info>
		<FileType>NeoBook Cartoon</FileType>
		<Ext>CAR</Ext>
		<Mime>application/octet-stream</Mime>
		<ExtraInfo>
			<Rem>Windows authoring software by NeoSoftware Corp.</Rem>
			<RefURL>https://www.neosoftware.com/</RefURL>
		</ExtraInfo>
		<User>Marco Pontello</User>
		<E-Mail>marcopon@gmail.com</E-Mail>
		<Home>http://mark0.net</Home>
	</Info>
	<General>
		<FileNum>3</FileNum>
		<Date>
			<Year>2019</Year>
			<Month>2</Month>
			<Day>1</Day>
		</Date>
		<Time>
			<Hour>14</Hour>
			<Min>57</Min>
			<Sec>37</Sec>
		</Time>
		<Creator>TrIDScan/Py v2.02</Creator>
	</General>
	<FrontBlock>
		<Pattern>
			<Bytes>534E0C00</Bytes>
			<ASCII> S N</ASCII>
			<Pos>0</Pos>
		</Pattern>
		<Pattern>
			<Bytes>0089504E470D0A1A0A0000000D49484452</Bytes>
			<ASCII> . . P N G . . . . . . . . I H D R</ASCII>
			<Pos>11</Pos>
		</Pattern>
	</FrontBlock>
</TrID>