<TrID ver="2.00">
	<Info>
		<FileType>TrueType Font Collection (v2)</FileType>
		<Ext>TTC</Ext>
		<Mime>application/font-sfnt</Mime>
		<ExtraInfo>
			<Rem></Rem>
			<RefURL>https://en.wikipedia.org/wiki/TrueType</RefURL>
		</ExtraInfo>
		<User>Joerg Jenderek</User>
		<E-Mail>joerg.jen.der.ek@gmx.net</E-Mail>
		<Home></Home>
	</Info>
	<General>
		<FileNum>47</FileNum>
		<CheckStrings>True</CheckStrings>
		<Date>
			<Year>2017</Year>
			<Month>6</Month>
			<Day>25</Day>
		</Date>
		<Time>
			<Hour>21</Hour>
			<Min>41</Min>
			<Sec>5</Sec>
		</Time>
		<Creator>TrIDScan/Py v2.02</Creator>
	</General>
	<FrontBlock>
		<Pattern>
			<Bytes>7474636600020000000000</Bytes>
			<ASCII> t t c f</ASCII>
			<Pos>0</Pos>
		</Pattern>
		<Pattern>
			<Bytes>000000</Bytes>
			<Pos>12</Pos>
		</Pattern>
		<Pattern>
			<Bytes>0000</Bytes>
			<Pos>16</Pos>
		</Pattern>
	</FrontBlock>
	<GlobalStrings>
		<String>CMAP</String>
		<String>GLYF</String>
		<String>HEAD</String>
		<String>HHEA</String>
		<String>HMTX</String>
		<String>LOCA</String>
		<String>MAXP</String>
		<String>NAME</String>
		<String>POST</String>
	</GlobalStrings>
</TrID>
