<TrID ver="2.00">
	<Info>
		<FileType>Astound Actor</FileType>
		<Ext>ACT</Ext>
		<Mime>application/octet-stream</Mime>
		<ExtraInfo>
			<Rem>Presentations/multimedia authoring program for Windows.</Rem>
			<RefURL></RefURL>
		</ExtraInfo>
		<User>Marco Pontello</User>
		<E-Mail>marcopon@gmail.com</E-Mail>
		<Home>http://mark0.net</Home>
	</Info>
	<General>
		<FileNum>322</FileNum>
		<CheckStrings>True</CheckStrings>
		<Date>
			<Year>2018</Year>
			<Month>4</Month>
			<Day>1</Day>
		</Date>
		<Time>
			<Hour>21</Hour>
			<Min>18</Min>
			<Sec>58</Sec>
		</Time>
		<Creator>TrIDScan/Py v2.02</Creator>
	</General>
	<FrontBlock>
		<Pattern>
			<Bytes>41435452</Bytes>
			<ASCII> A C T R</ASCII>
			<Pos>0</Pos>
		</Pattern>
		<Pattern>
			<Bytes>7073</Bytes>
			<ASCII> p s</ASCII>
			<Pos>8</Pos>
		</Pattern>
	</FrontBlock>
	<GlobalStrings>
		<String>DWRB</String>
		<String>NNDN</String>
		<String>NNEL</String>
		<String>PSNM</String>
		<String>PTEX</String>
		<String>PTPS</String>
		<String>PTRG</String>
		<String>WDKD</String>
	</GlobalStrings>
</TrID>