<TrID ver="2.00">
	<Info>
		<FileType>PARIS Audio Format audio (little-endian)</FileType>
		<Ext>FAP</Ext>
		<Mime>application/octet-stream</Mime>
		<ExtraInfo>
			<Rem>PARIS stands for Professional Audio Recording Integrated System.</Rem>
			<RefURL>https://en.wikipedia.org/wiki/Ensoniq_Paris</RefURL>
		</ExtraInfo>
		<User>Marco Pontello</User>
		<E-Mail>marcopon@gmail.com</E-Mail>
		<Home>http://mark0.net</Home>
	</Info>
	<General>
		<FileNum>4</FileNum>
		<Refine>1 by Marco Pontello</Refine>
		<Date>
			<Year>2023</Year>
			<Month>10</Month>
			<Day>28</Day>
		</Date>
		<Time>
			<Hour>20</Hour>
			<Min>7</Min>
			<Sec>23</Sec>
		</Time>
		<Creator>TrIDScan/Py v2.02</Creator>
	</General>
	<FrontBlock>
		<Pattern>
			<Bytes>66617020</Bytes>
			<ASCII> f a p</ASCII>
			<Pos>0</Pos>
		</Pattern>
	</FrontBlock>
</TrID>