<TrID ver="2.00">
	<Info>
		<FileType>XTimeTable Time Table</FileType>
		<Ext>XTT</Ext>
		<Mime>text/plain</Mime>
		<ExtraInfo>
			<Rem></Rem>
			<RefURL>ftp://hpux.connect.org.uk/hpux/X11/Demos/xtt-1.0/xtt-1.0.README.html</RefURL>
		</ExtraInfo>
		<User>Marco Pontello</User>
		<E-Mail>marcopon@gmail.com</E-Mail>
		<Home>http://mark0.net</Home>
	</Info>
	<General>
		<FileNum>3</FileNum>
		<Date>
			<Year>2016</Year>
			<Month>9</Month>
			<Day>15</Day>
		</Date>
		<Time>
			<Hour>17</Hour>
			<Min>9</Min>
			<Sec>4</Sec>
		</Time>
		<Creator>TrIDScan/Py v2.02</Creator>
	</General>
	<FrontBlock>
		<Pattern>
			<Bytes>2320787474</Bytes>
			<ASCII> #   x t t</ASCII>
			<Pos>0</Pos>
		</Pattern>
	</FrontBlock>
</TrID>