<TrID ver="2.00">
	<Info>
		<FileType>SuperScape world/scene data</FileType>
		<Ext>VRT</Ext>
		<Mime>application/octet-stream</Mime>
		<ExtraInfo>
			<Rem></Rem>
			<RefURL>https://en.wikipedia.org/wiki/Superscape</RefURL>
		</ExtraInfo>
		<User>Marco Pontello</User>
		<E-Mail>marcopon@gmail.com</E-Mail>
		<Home>https://mark0.net</Home>
	</Info>
	<General>
		<FileNum>2</FileNum>
		<Date>
			<Year>2025</Year>
			<Month>3</Month>
			<Day>18</Day>
		</Date>
		<Time>
			<Hour>3</Hour>
			<Min>38</Min>
			<Sec>10</Sec>
		</Time>
		<Creator>TrIDScan/Py v2.02</Creator>
	</General>
	<FrontBlock>
		<Pattern>
			<Bytes>5375706572536361706520286329204E65772044696D656E73696F6E20496E7465726E6174696F6E616C204C74642E000A0A0D5652542066696C65</Bytes>
			<ASCII> S u p e r S c a p e   ( c )   N e w   D i m e n s i o n   I n t e r n a t i o n a l   L t d . . . . . V R T   f i l e</ASCII>
			<Pos>0</Pos>
		</Pattern>
	</FrontBlock>
</TrID>