<TrID ver="2.00">
	<Info>
		<FileType>Z/Install forms/Dialogs</FileType>
		<Ext>VVD</Ext>
		<Mime>application/octet-stream</Mime>
		<ExtraInfo>
			<Rem></Rem>
			<RefURL>http://fileformats.archiveteam.org/wiki/Zilite</RefURL>
		</ExtraInfo>
		<User>Marco Pontello</User>
		<E-Mail>marcopon@gmail.com</E-Mail>
		<Home>https://mark0.net</Home>
	</Info>
	<General>
		<FileNum>14</FileNum>
		<CheckStrings>True</CheckStrings>
		<Date>
			<Year>2022</Year>
			<Month>11</Month>
			<Day>3</Day>
		</Date>
		<Time>
			<Hour>19</Hour>
			<Min>2</Min>
			<Sec>16</Sec>
		</Time>
		<Creator>TrIDScan/Py v2.02</Creator>
	</General>
	<FrontBlock>
		<Pattern>
			<Bytes>FFFF460000005647</Bytes>
			<ASCII> . . F . . . V G</ASCII>
			<Pos>0</Pos>
		</Pattern>
		<Pattern>
			<Bytes>0000000000FDFF28000000</Bytes>
			<ASCII> . . . . . . . (</ASCII>
			<Pos>65</Pos>
		</Pattern>
	</FrontBlock>
	<GlobalStrings>
		<String>FM_BEGIN</String>
		<String>FM_END</String>
	</GlobalStrings>
</TrID>