<TrID ver="2.00">
	<Info>
		<FileType>3D Movie Maker (generic)</FileType>
		<Ext>3MM/3TH/CHK/3CN</Ext>
		<Mime>application/octet-stream</Mime>
		<ExtraInfo>
			<Rem></Rem>
			<RefURL>http://fileformats.archiveteam.org/wiki/3D_Movie_Maker</RefURL>
		</ExtraInfo>
		<User>Marco Pontello</User>
		<E-Mail>marcopon@gmail.com</E-Mail>
		<Home>https://mark0.net</Home>
	</Info>
	<General>
		<FileNum>63</FileNum>
		<Refine>56 by Marco Pontello</Refine>
		<Date>
			<Year>2024</Year>
			<Month>5</Month>
			<Day>18</Day>
		</Date>
		<Time>
			<Hour>21</Hour>
			<Min>1</Min>
			<Sec>17</Sec>
		</Time>
		<Creator>TrIDScan/Py v2.02</Creator>
	</General>
	<FrontBlock>
		<Pattern>
			<Bytes>43484E32</Bytes>
			<ASCII> C H N 2</ASCII>
			<Pos>0</Pos>
		</Pattern>
	</FrontBlock>
</TrID>