<TrID ver="2.00">
	<Info>
		<FileType>FinalBuilder Project (v4) / Automise Project (v1)</FileType>
		<Ext>FBP4/ATP</Ext>
		<Mime>text/xml</Mime>
		<ExtraInfo>
			<Rem></Rem>
			<RefURL>https://en.wikipedia.org/wiki/Automise</RefURL>
		</ExtraInfo>
		<User>Marco Pontello</User>
		<E-Mail>marcopon@gmail.com</E-Mail>
		<Home>http://mark0.net</Home>
	</Info>
	<General>
		<FileNum>9</FileNum>
		<CheckStrings>True</CheckStrings>
		<Date>
			<Year>2019</Year>
			<Month>9</Month>
			<Day>23</Day>
		</Date>
		<Time>
			<Hour>14</Hour>
			<Min>23</Min>
			<Sec>41</Sec>
		</Time>
		<Creator>TrIDScan/Py v2.02</Creator>
	</General>
	<FrontBlock>
		<Pattern>
			<Bytes>3C3F786D6C2076657273696F6E3D22312E302220656E636F64696E673D225554462D38223F3E0D0A3C5653584D4C3E</Bytes>
			<ASCII> . ? x m l   v e r s i o n = " 1 . 0 "   e n c o d i n g = " U T F - 8 " ? . . . . V S X M L</ASCII>
			<Pos>0</Pos>
		</Pattern>
	</FrontBlock>
	<GlobalStrings>
		<String>{281C7779-6D60-46CB-AC57-38DC6487F564}</String>
		<String>{3A0B409D-3DC9-4E8B-8001-28926E75AA46}</String>
		<String>{4D6595B8-7483-40F9-8FDA-D6FA11856C94}</String>
		<String>TFBACTIONLISTPARAMETERSCOLLECTION</String>
		<String>TFBACTIONLISTCOLLECTION</String>
		<String>SUPPRESSSTATUSMESSAGES</String>
		<String>TFBVARIABLESCOLLECTION</String>
		<String>ENCRYPTEDEDITPASSWORD</String>
		<String>EXPANDACTIONLOGTITLE</String>
		<String>PROPERTY MULTIVALUE</String>
		<String>FINALBUILDERACTION</String>
		<String>RETRYPAUSEINTERVAL</String>
		<String>MAXRETRYATTEMPTS</String>
		<String>GLOBALVBSCRIPT</String>
		<String>TCOMMENTACTION</String>
		<String>ACTIONCOMMENT</String>
		<String>GLOBALJSCRIPT</String>
		<String>IGNOREFAILURE</String>
		<String>LOGTOVARIABLE</String>
		<String>NODECOLLAPSED</String>
		<String>PROPERTY NAME</String>
		<String>ACTIONTYPEID</String>
		<String>ISBREAKPOINT</String>
		<String>OBJECT CLASS</String>
		<String>DESCRIPTION</String>
		<String>TFBPROJECT</String>
		<String>WIDESTRING</String>
		<String>ISFAILURE</String>
		<String>ONFAILURE</String>
		<String>PROJECTID</String>
		<String>CARDINAL</String>
		<String>ISACTION</String>
		<String>UNIQUEID</String>
		<String>WORDBOOL</String>
		<String>BOOLEAN</String>
		<String>ENABLED</String>
		<String>ISMAIN</String>
		<String>FALSE</String>
		<String>VSXML</String>
		<String>XMLID</String>
		<String>1000</String>
		<String>TRUE</String>
	</GlobalStrings>
</TrID>