<TrID ver="2.00">
	<Info>
		<FileType>Digital Reality Software Maps data</FileType>
		<Ext>MAPS</Ext>
		<Mime>application/octet-stream</Mime>
		<ExtraInfo>
			<Rem></Rem>
			<RefURL>https://en.wikipedia.org/wiki/Digital_Reality</RefURL>
		</ExtraInfo>
		<User>Marco Pontello</User>
		<E-Mail>marcopon@gmail.com</E-Mail>
		<Home>https://mark0.net</Home>
	</Info>
	<General>
		<FileNum>51</FileNum>
		<CheckStrings>True</CheckStrings>
		<Date>
			<Year>2023</Year>
			<Month>11</Month>
			<Day>25</Day>
		</Date>
		<Time>
			<Hour>3</Hour>
			<Min>26</Min>
			<Sec>8</Sec>
		</Time>
		<Creator>TrIDScan/Py v2.02</Creator>
	</General>
	<FrontBlock>
		<Pattern>
			<Bytes>5465727261696E4D6170734865696768744D61700000</Bytes>
			<ASCII> T e r r a i n M a p s H e i g h t M a p</ASCII>
			<Pos>0</Pos>
		</Pattern>
	</FrontBlock>
	<GlobalStrings>
		<String>STATICFOWMAP</String>
		<String>TILEMAPBLEND</String>
		<String>PASSABILITY</String>
		<String>VISIBILITY</String>
	</GlobalStrings>
</TrID>