<TrID ver="2.00">
	<Info>
		<FileType>MINC2 Medical Imaging format</FileType>
		<Ext>MNC</Ext>
		<Mime>application/octet-stream</Mime>
		<ExtraInfo>
			<Rem></Rem>
			<RefURL>http://fileformats.archiveteam.org/wiki/MINC</RefURL>
		</ExtraInfo>
		<User>Marco Pontello</User>
		<E-Mail>marcopon@gmail.com</E-Mail>
		<Home>http://mark0.net</Home>
	</Info>
	<General>
		<FileNum>48</FileNum>
		<Refine>24 by Marco Pontello</Refine>
		<CheckStrings>True</CheckStrings>
		<Date>
			<Year>2017</Year>
			<Month>9</Month>
			<Day>22</Day>
		</Date>
		<Time>
			<Hour>22</Hour>
			<Min>48</Min>
			<Sec>32</Sec>
		</Time>
		<Creator>TrIDScan/Py v2.02</Creator>
	</General>
	<FrontBlock>
		<Pattern>
			<Bytes>894844460D0A1A0A</Bytes>
			<ASCII> . H D F</ASCII>
			<Pos>0</Pos>
		</Pattern>
	</FrontBlock>
	<GlobalStrings>
		<String>Y INCREASES FROM PATIENT POSTERIOR TO ANTERIOR</String>
		<String>Z INCREASES FROM PATIENT INFERIOR TO SUPERIOR</String>
		<String>X INCREASES FROM PATIENT LEFT TO RIGHT</String>
		<String>MINC STANDARD VARIABLE</String>
		<String>VAR_ATTRIBUTE</String>
		<String>MINC VERSION</String>
		<String>DIMENSIONS</String>
		<String>ALIGNMENT</String>
		<String>IMAGE-MAX</String>
		<String>IMAGE-MIN</String>
		<String>COMMENTS</String>
		<String>COMPLETE</String>
		<String>DIMORDER</String>
		<String>MINC-2.0</String>
		<String>HISTORY</String>
		<String>REGULAR</String>
		<String>SPACING</String>
		<String>VARTYPE</String>
		<String>CENTRE</String>
		<String>LENGTH</String>
		<String>VFONOV</String>
		<String>XSPACE</String>
		<String>YSPACE</String>
		<String>ZSPACE</String>
		<String>GROUP</String>
		<String>IDENT</String>
		<String>START</String>
		<String>TRUE_</String>
		<String>VARID</String>
		<String>.MNC</String>
		<String>HEAP</String>
		<String>INFO</String>
		<String>SNOD</String>
		<String>STEP</String>
		<String>TREE</String>
	</GlobalStrings>
</TrID>