<TrID ver="2.00">
	<Info>
		<FileType>PSGMOD module</FileType>
		<Ext>PSGMOD</Ext>
		<Mime>audio/x-mod</Mime>
		<ExtraInfo>
			<Rem></Rem>
			<RefURL></RefURL>
		</ExtraInfo>
		<User>Marco Pontello</User>
		<E-Mail>marcopon@gmail.com</E-Mail>
		<Home>http://mark0.net</Home>
	</Info>
	<General>
		<FileNum>8</FileNum>
		<CheckStrings>True</CheckStrings>
		<Date>
			<Year>2019</Year>
			<Month>9</Month>
			<Day>1</Day>
		</Date>
		<Time>
			<Hour>16</Hour>
			<Min>48</Min>
			<Sec>47</Sec>
		</Time>
		<Creator>TrIDScan/Py v2.02</Creator>
	</General>
	<FrontBlock>
		<Pattern>
			<Bytes>5053474D4F442D3248454144</Bytes>
			<ASCII> P S G M O D - 2 H E A D</ASCII>
			<Pos>0</Pos>
		</Pattern>
	</FrontBlock>
	<GlobalStrings>
		<String>INFO</String>
		<String>INST</String>
		<String>PATS</String>
		<String>PATT</String>
	</GlobalStrings>
</TrID>