<TrID ver="2.00">
	<Info>
		<FileType>PS2 generic game data container</FileType>
		<Ext>MRG/MZP</Ext>
		<Mime>application/octet-stream</Mime>
		<ExtraInfo>
			<Rem></Rem>
			<RefURL></RefURL>
		</ExtraInfo>
		<User>Marco Pontello</User>
		<E-Mail>marcopon@gmail.com</E-Mail>
		<Home>https://mark0.net</Home>
	</Info>
	<General>
		<FileNum>4</FileNum>
		<Date>
			<Year>2024</Year>
			<Month>8</Month>
			<Day>3</Day>
		</Date>
		<Time>
			<Hour>14</Hour>
			<Min>9</Min>
			<Sec>29</Sec>
		</Time>
		<Creator>TrIDScan/Py v2.02</Creator>
	</General>
	<FrontBlock>
		<Pattern>
			<Bytes>6D7267643030</Bytes>
			<ASCII> m r g d 0 0</ASCII>
			<Pos>0</Pos>
		</Pattern>
	</FrontBlock>
</TrID>