<TrID ver="2.00">
	<Info>
		<FileType>EMSA/MAS Spectral Data</FileType>
		<Ext>MSA</Ext>
		<Mime>text/plain</Mime>
		<ExtraInfo>
			<Rem></Rem>
			<RefURL>http://fileformats.archiveteam.org/wiki/EMSA/MAS</RefURL>
		</ExtraInfo>
		<User>Marco Pontello</User>
		<E-Mail>marcopon@gmail.com</E-Mail>
		<Home>https://mark0.net</Home>
	</Info>
	<General>
		<FileNum>39</FileNum>
		<CheckStrings>True</CheckStrings>
		<Date>
			<Year>2022</Year>
			<Month>1</Month>
			<Day>19</Day>
		</Date>
		<Time>
			<Hour>2</Hour>
			<Min>5</Min>
			<Sec>5</Sec>
		</Time>
		<Creator>TrIDScan/Py v2.02</Creator>
	</General>
	<FrontBlock>
		<Pattern>
			<Bytes>23464F524D415420</Bytes>
			<ASCII> # F O R M A T</ASCII>
			<Pos>0</Pos>
		</Pattern>
	</FrontBlock>
	<GlobalStrings>
		<String>MAS SPECTRAL DATA</String>
		<String>ENDOFDATA</String>
		<String>DATATYPE</String>
		<String>NCOLUMNS</String>
		<String>SPECTRUM</String>
		<String>XPERCHAN</String>
		<String>NPOINTS</String>
		<String>VERSION</String>
		<String>BEAMKV</String>
		<String>ENERGY</String>
		<String>OFFSET</String>
		<String>XLABEL</String>
		<String>XUNITS</String>
		<String>YLABEL</String>
		<String>YUNITS</String>
		<String>OWNER</String>
		<String>TITLE</String>
		<String>DATE</String>
		<String>EMSA</String>
		<String>TIME</String>
	</GlobalStrings>
</TrID>